kodiksnlp/__init__.py
kodiksnlp/preprocessing.py
kodiksnlp/similarity.py
kodiksnlp/wordembedding.py
kodiksnlp-0.0.7.dist-info/LICENSE
kodiksnlp-0.0.7.dist-info/METADATA
kodiksnlp-0.0.7.dist-info/WHEEL
kodiksnlp-0.0.7.dist-info/top_level.txt
kodiksnlp-0.0.7.dist-info/RECORD
