Metadata-Version: 2.1
Name: kodiksnlp
Version: 0.0.7
Summary: Kodiks Turkish NLP Tool
Home-page: https://gitlab.com/kodiks-ai/kodiksnlp
Author: Yavuz Kömeçoğlu
Author-email: yavuz.komecoglu@kodiks.com
License: UNKNOWN
Platform: UNKNOWN
Classifier: Programming Language :: Python :: 3
Classifier: License :: OSI Approved :: MIT License
Classifier: Operating System :: OS Independent
Requires-Python: >=3.5
Requires-Dist: requests (>=2.21.0)
